apteryx/__init__.py
apteryx/google/__init__.py
apteryx/google/storage.py
apteryx/types.py
apteryx/utils/__init__.py
apteryx/utils/decorators.py
apteryx/utils/functions.py
apteryx/utils/http/__init__.py
apteryx/utils/http/networking.py
apteryx/utils/http/parallel.py
apteryx-1.0.11.dist-info/WHEEL
apteryx-1.0.11.dist-info/METADATA
apteryx-1.0.11.dist-info/RECORD
